pyquickhelper/__init__.py
pyquickhelper/__main__.py
pyquickhelper/_cst/__init__.py
pyquickhelper/_cst/cst_sphinx.py
pyquickhelper/benchhelper/__init__.py
pyquickhelper/benchhelper/benchmark.py
pyquickhelper/benchhelper/grid_benchmark.py
pyquickhelper/cli/__init__.py
pyquickhelper/cli/cli_helper.py
pyquickhelper/cli/encryption_cli.py
pyquickhelper/cli/encryption_file_cli.py
pyquickhelper/cli/ftp_cli.py
pyquickhelper/cli/notebook.py
pyquickhelper/cli/profile_cli.py
pyquickhelper/cli/pyq_sync_cli.py
pyquickhelper/cli/script_exec.py
pyquickhelper/cli/simplified_fct.py
pyquickhelper/cli/uvicorn_cli.py
pyquickhelper/filehelper/__init__.py
pyquickhelper/filehelper/anyfhelper.py
pyquickhelper/filehelper/compression_helper.py
pyquickhelper/filehelper/difflib.js
pyquickhelper/filehelper/diffview.css
pyquickhelper/filehelper/diffview.js
pyquickhelper/filehelper/download_helper.py
pyquickhelper/filehelper/download_urls_helper.py
pyquickhelper/filehelper/encrypted_backup.py
pyquickhelper/filehelper/encryption.py
pyquickhelper/filehelper/fexceptions.py
pyquickhelper/filehelper/file_info.py
pyquickhelper/filehelper/file_tree_node.py
pyquickhelper/filehelper/files_status.py
pyquickhelper/filehelper/ftp_mock.py
pyquickhelper/filehelper/ftp_transfer.py
pyquickhelper/filehelper/ftp_transfer_files.py
pyquickhelper/filehelper/ftp_transfer_mock.py
pyquickhelper/filehelper/internet_helper.py
pyquickhelper/filehelper/synchelper.py
pyquickhelper/filehelper/transfer_api.py
pyquickhelper/filehelper/transfer_api_file.py
pyquickhelper/filehelper/transfer_api_ftp.py
pyquickhelper/filehelper/visual_sync.py
pyquickhelper/filehelper/winzipfile.py
pyquickhelper/helpgen/__init__.py
pyquickhelper/helpgen/_fake_function_to_documentation.py
pyquickhelper/helpgen/_my_doxypy.py
pyquickhelper/helpgen/_nbconvert_config.py
pyquickhelper/helpgen/_nbconvert_preprocessor.py
pyquickhelper/helpgen/_single_file_html_builder.py
pyquickhelper/helpgen/conf_path_tools.py
pyquickhelper/helpgen/default_conf.py
pyquickhelper-1.11.3744.dist-info/LICENSE.txt
pyquickhelper-1.11.3744.dist-info/METADATA
pyquickhelper-1.11.3744.dist-info/WHEEL
pyquickhelper-1.11.3744.dist-info/entry_points.txt
pyquickhelper-1.11.3744.dist-info/top_level.txt
pyquickhelper-1.11.3744.dist-info/RECORD
