Metadata-Version: 2.1
Name: pyquickhelper
Version: 1.11.3744
Summary: Various functionalities: folder synchronization, simple logging function, helpers to generate documentation with sphinx, sphinx extension, to run a command line, to run a notebook...
Home-page: http://www.xavierdupre.fr/app/pyquickhelper/helpsphinx/index.html
Author: Xavier Dupré
Author-email: xavier.dupre@gmail.com
License: MIT
Download-URL: https://github.com/sdpython/pyquickhelper
Keywords: pyquickhelper,synchronization, files,documentation,Xavier Dupré,sphinx,notebooks,rst,helpers,automation
Platform: UNKNOWN
Classifier: Programming Language :: Python :: 3
Classifier: Intended Audience :: Developers
Classifier: Topic :: Software Development :: Build Tools
Classifier: License :: OSI Approved :: MIT License
Classifier: Development Status :: 5 - Production/Stable
Requires-Dist: fire
Requires-Dist: numpy (>=1.16.0)
Requires-Dist: pyquicksetup (>=0.2)
Provides-Extra: all
Requires-Dist: autopep8 ; extra == 'all'
Requires-Dist: cffi ; extra == 'all'
Requires-Dist: coverage (>=5.0) ; extra == 'all'
Requires-Dist: cryptography ; extra == 'all'
Requires-Dist: docformatter ; extra == 'all'
Requires-Dist: docutils ; extra == 'all'
Requires-Dist: flake8 ; extra == 'all'
Requires-Dist: fastapi ; extra == 'all'
Requires-Dist: fire ; extra == 'all'
Requires-Dist: IPython (>=5.0.0) ; extra == 'all'
Requires-Dist: jupyter ; extra == 'all'
Requires-Dist: jupyter-client ; extra == 'all'
Requires-Dist: jupyter-sphinx ; extra == 'all'
Requires-Dist: jyquickhelper ; extra == 'all'
Requires-Dist: keyring ; extra == 'all'
Requires-Dist: keyrings.cryptfile ; extra == 'all'
Requires-Dist: matplotlib ; extra == 'all'
Requires-Dist: metakernel ; extra == 'all'
Requires-Dist: multi-key-dict ; extra == 'all'
Requires-Dist: nbconvert (!=6.3.0,!=6.4.0,!=6.4.1,!=6.5.0,>=6.0.3) ; extra == 'all'
Requires-Dist: notebook (>=4.2.0) ; extra == 'all'
Requires-Dist: numpy (>=1.16.0) ; extra == 'all'
Requires-Dist: numpydoc ; extra == 'all'
Requires-Dist: pandas (>=1.0.0) ; extra == 'all'
Requires-Dist: psutil ; extra == 'all'
Requires-Dist: pylint ; extra == 'all'
Requires-Dist: python-jenkins (>=1.0.0) ; extra == 'all'
Requires-Dist: pyyaml ; extra == 'all'
Requires-Dist: pylzma ; extra == 'all'
Requires-Dist: pysftp ; extra == 'all'
Requires-Dist: requests ; extra == 'all'
Requires-Dist: semantic-version ; extra == 'all'
Requires-Dist: sphinx (>=3.0) ; extra == 'all'
Requires-Dist: sphinx-gallery ; extra == 'all'
Requires-Dist: sphinxcontrib-imagesvg ; extra == 'all'
Requires-Dist: traitlets (>=5.0) ; extra == 'all'
Provides-Extra: cli
Requires-Dist: tkinterquickhelper ; extra == 'cli'
Requires-Dist: pysftp ; extra == 'cli'
Requires-Dist: fire ; extra == 'cli'
Provides-Extra: filehelper
Requires-Dist: cffi ; extra == 'filehelper'
Requires-Dist: cryptography ; extra == 'filehelper'
Requires-Dist: pylzma ; extra == 'filehelper'
Requires-Dist: pysftp ; extra == 'filehelper'
Requires-Dist: keyrings.cryptfile ; extra == 'filehelper'
Provides-Extra: jenkinshelper
Requires-Dist: python-jenkins (>=1.0.0) ; extra == 'jenkinshelper'
Requires-Dist: pyyaml ; extra == 'jenkinshelper'
Provides-Extra: loghelper
Requires-Dist: psutil ; extra == 'loghelper'
Provides-Extra: server
Requires-Dist: fastapi ; extra == 'server'
